cli/__init__.py
cli/app.py
cli/constants.py
cli/discovery.py
cli/errors.py
cli/main.py
cli/status_plugin.py
cli/utils.py
cli/yaml_edit.py
cli/screens/__init__.py
cli/screens/create_experiment.py
cli/screens/delete_data.py
cli/screens/load_error.py
cli/screens/loading.py
cli/screens/run.py
cli/screens/selection.py
cli/screens/selection_screens.py
cli/screens/style/create_experiment.py
cli/screens/style/run.py
cli/widgets/__init__.py
cli/widgets/config_editor.py
cli/widgets/writer.py
cli/widgets/style/config_editor.py
crystallize/__init__.py
crystallize/datasources/__init__.py
crystallize/datasources/artifacts.py
crystallize/datasources/datasource.py
crystallize/datasources/registry.py
crystallize/experiments/__init__.py
crystallize/experiments/aggregation.py
crystallize/experiments/experiment.py
crystallize/experiments/experiment_builder.py
crystallize/experiments/experiment_graph.py
crystallize/experiments/hypothesis.py
crystallize/experiments/optimizers.py
crystallize/experiments/result.py
crystallize/experiments/result_structs.py
crystallize/experiments/run_results.py
crystallize/experiments/treatment.py
crystallize/pipelines/__init__.py
crystallize/pipelines/pipeline.py
crystallize/pipelines/pipeline_step.py
crystallize/plugins/__init__.py
crystallize/plugins/artifacts.py
crystallize/plugins/execution.py
crystallize/plugins/plugins.py
crystallize/utils/__init__.py
crystallize/utils/cache.py
crystallize/utils/constants.py
crystallize/utils/context.py
crystallize/utils/decorators.py
crystallize/utils/exceptions.py
crystallize/utils/injection.py
crystallize_ml-0.27.0.dist-info/licenses/LICENSE
crystallize_ml-0.27.0.dist-info/METADATA
crystallize_ml-0.27.0.dist-info/WHEEL
crystallize_ml-0.27.0.dist-info/entry_points.txt
crystallize_ml-0.27.0.dist-info/top_level.txt
crystallize_ml-0.27.0.dist-info/RECORD
