Metadata-Version: 2.4
Name: crystallize-ml
Version: 0.27.0
Summary: A framework for reproducible experiments with pipelines, treatments, and hypotheses.
Author-email: Bryson Tang <brysontang@gmail.com>
License: MIT
Project-URL: Homepage, https://github.com/brysontang/crystallize
Project-URL: Documentation, https://github.com/brysontang/crystallize/tree/main/docs
Classifier: Programming Language :: Python :: 3
Classifier: License :: OSI Approved :: MIT License
Classifier: Operating System :: OS Independent
Requires-Python: >=3.10
License-File: LICENSE
Requires-Dist: pyyaml<7,>=6.0.2
Requires-Dist: networkx<4,>=3.4.2
Requires-Dist: tqdm
Requires-Dist: rich<14,>=13.8.1
Requires-Dist: dill<0.4,>=0.3.7
Requires-Dist: textual<6,>=5.0.1
Requires-Dist: textual-serve<2,>=1.1.2
Requires-Dist: python-dotenv<2,>=1.0.1
Provides-Extra: dev
Provides-Extra: extras
Requires-Dist: crystallize-extras; extra == "extras"
Provides-Extra: ray
Requires-Dist: ray; extra == "ray"
Provides-Extra: vllm
Requires-Dist: vllm; extra == "vllm"
Provides-Extra: cli
Requires-Dist: textual; extra == "cli"
Provides-Extra: all
Requires-Dist: crystallize-extras; extra == "all"
Requires-Dist: ray; extra == "all"
Requires-Dist: vllm; extra == "all"
Requires-Dist: textual; extra == "all"
Dynamic: license-file
